<?xml version="1.0" encoding="UTF-8"?>
<!DOCTYPE mapper PUBLIC "-//mybatis.org//DTD Mapper 3.0//EN" "http://mybatis.org/dtd/mybatis-3-mapper.dtd">
<mapper namespace="com.ipaylinks.cmp.css.dal.mapper.WithdrawVoucherMapper">
  <resultMap id="BaseResultMap" type="com.ipaylinks.cmp.css.dal.model.WithdrawVoucher">
    <!--
      @MBG Generated
      This element is automatically generated by MyBatis Generator,Do not modify ! Generated on Thu May 24 17:03:46 CST 2018.
    -->
    <id column="ID" jdbcType="VARCHAR" property="id" />
    <result column="MERCHANT_ID" jdbcType="VARCHAR" property="merchantId" />
    <result column="FUNDOUT_TIME" jdbcType="TIMESTAMP" property="fundoutTime" />
    <result column="FUNDOUT_CURRENCY_CODE" jdbcType="VARCHAR" property="fundoutCurrencyCode" />
    <result column="FUNDOUT_AMOUNT" jdbcType="DECIMAL" property="fundoutAmount" />
    <result column="BEGIN_DATE" jdbcType="VARCHAR" property="beginDate" />
    <result column="END_DATE" jdbcType="VARCHAR" property="endDate" />
    <result column="FUNDOUT_TYPE" jdbcType="VARCHAR" property="fundoutType" />
    <result column="AUTO_FUNDOUT_FLAG" jdbcType="VARCHAR" property="autoFundoutFlag" />
    <result column="FUNDOUT_STATUS" jdbcType="VARCHAR" property="fundoutStatus" />
    <result column="FUNDOUT_ID" jdbcType="VARCHAR" property="fundoutId" />
    <result column="FUNDOUT_REQUEST_TIME" jdbcType="TIMESTAMP" property="fundoutRequestTime" />
    <result column="FUNDOUT_COMPLETE_TIME" jdbcType="TIMESTAMP" property="fundoutCompleteTime" />
    <result column="GMT_CREATE_TIME" jdbcType="TIMESTAMP" property="gmtCreateTime" />
    <result column="GMT_UPDATE_TIME" jdbcType="TIMESTAMP" property="gmtUpdateTime" />
  </resultMap>
  <sql id="Base_Column_List">
    <!--
      @MBG Generated
      This element is automatically generated by MyBatis Generator,Do not modify ! Generated on Thu May 24 17:03:46 CST 2018.
    -->
    ID, MERCHANT_ID, FUNDOUT_TIME, FUNDOUT_CURRENCY_CODE, FUNDOUT_AMOUNT, BEGIN_DATE, 
    END_DATE, FUNDOUT_TYPE, AUTO_FUNDOUT_FLAG, FUNDOUT_STATUS, FUNDOUT_ID, FUNDOUT_REQUEST_TIME, 
    FUNDOUT_COMPLETE_TIME, GMT_CREATE_TIME, GMT_UPDATE_TIME
  </sql>
  <select id="selectByPrimaryKey" parameterType="java.lang.String" resultMap="BaseResultMap">
    <!--
      @MBG Generated
      This element is automatically generated by MyBatis Generator,Do not modify ! Generated on Thu May 24 17:03:46 CST 2018.
    -->
    select 
    <include refid="Base_Column_List" />
    from T_WITHDRAW_VOUCHER
    where ID = #{id,jdbcType=VARCHAR}
  </select>
  <delete id="deleteByPrimaryKey" parameterType="java.lang.String">
    <!--
      @MBG Generated
      This element is automatically generated by MyBatis Generator,Do not modify ! Generated on Thu May 24 17:03:46 CST 2018.
    -->
    delete from T_WITHDRAW_VOUCHER
    where ID = #{id,jdbcType=VARCHAR}
  </delete>
  <insert id="insert" parameterType="com.ipaylinks.cmp.css.dal.model.WithdrawVoucher">
    <!--
      @MBG Generated
      This element is automatically generated by MyBatis Generator,Do not modify ! Generated on Thu May 24 17:03:46 CST 2018.
    -->
    insert into T_WITHDRAW_VOUCHER (ID, MERCHANT_ID, FUNDOUT_TIME, 
      FUNDOUT_CURRENCY_CODE, FUNDOUT_AMOUNT, BEGIN_DATE, 
      END_DATE, FUNDOUT_TYPE, AUTO_FUNDOUT_FLAG, 
      FUNDOUT_STATUS, FUNDOUT_ID, FUNDOUT_REQUEST_TIME, 
      FUNDOUT_COMPLETE_TIME, GMT_CREATE_TIME, 
      GMT_UPDATE_TIME)
    values (#{id,jdbcType=VARCHAR}, #{merchantId,jdbcType=VARCHAR}, #{fundoutTime,jdbcType=TIMESTAMP}, 
      #{fundoutCurrencyCode,jdbcType=VARCHAR}, #{fundoutAmount,jdbcType=DECIMAL}, #{beginDate,jdbcType=VARCHAR}, 
      #{endDate,jdbcType=VARCHAR}, #{fundoutType,jdbcType=VARCHAR}, #{autoFundoutFlag,jdbcType=VARCHAR}, 
      #{fundoutStatus,jdbcType=VARCHAR}, #{fundoutId,jdbcType=VARCHAR}, #{fundoutRequestTime,jdbcType=TIMESTAMP}, 
      #{fundoutCompleteTime,jdbcType=TIMESTAMP}, #{gmtCreateTime,jdbcType=TIMESTAMP}, 
      #{gmtUpdateTime,jdbcType=TIMESTAMP})
  </insert>
  <insert id="insertSelective" parameterType="com.ipaylinks.cmp.css.dal.model.WithdrawVoucher">
    <!--
      @MBG Generated
      This element is automatically generated by MyBatis Generator,Do not modify ! Generated on Thu May 24 17:03:46 CST 2018.
    -->
    insert into T_WITHDRAW_VOUCHER
    <trim prefix="(" suffix=")" suffixOverrides=",">
      <if test="id != null">
        ID,
      </if>
      <if test="merchantId != null">
        MERCHANT_ID,
      </if>
      <if test="fundoutTime != null">
        FUNDOUT_TIME,
      </if>
      <if test="fundoutCurrencyCode != null">
        FUNDOUT_CURRENCY_CODE,
      </if>
      <if test="fundoutAmount != null">
        FUNDOUT_AMOUNT,
      </if>
      <if test="beginDate != null">
        BEGIN_DATE,
      </if>
      <if test="endDate != null">
        END_DATE,
      </if>
      <if test="fundoutType != null">
        FUNDOUT_TYPE,
      </if>
      <if test="autoFundoutFlag != null">
        AUTO_FUNDOUT_FLAG,
      </if>
      <if test="fundoutStatus != null">
        FUNDOUT_STATUS,
      </if>
      <if test="fundoutId != null">
        FUNDOUT_ID,
      </if>
      <if test="fundoutRequestTime != null">
        FUNDOUT_REQUEST_TIME,
      </if>
      <if test="fundoutCompleteTime != null">
        FUNDOUT_COMPLETE_TIME,
      </if>
      <if test="gmtCreateTime != null">
        GMT_CREATE_TIME,
      </if>
      <if test="gmtUpdateTime != null">
        GMT_UPDATE_TIME,
      </if>
    </trim>
    <trim prefix="values (" suffix=")" suffixOverrides=",">
      <if test="id != null">
        #{id,jdbcType=VARCHAR},
      </if>
      <if test="merchantId != null">
        #{merchantId,jdbcType=VARCHAR},
      </if>
      <if test="fundoutTime != null">
        #{fundoutTime,jdbcType=TIMESTAMP},
      </if>
      <if test="fundoutCurrencyCode != null">
        #{fundoutCurrencyCode,jdbcType=VARCHAR},
      </if>
      <if test="fundoutAmount != null">
        #{fundoutAmount,jdbcType=DECIMAL},
      </if>
      <if test="beginDate != null">
        #{beginDate,jdbcType=VARCHAR},
      </if>
      <if test="endDate != null">
        #{endDate,jdbcType=VARCHAR},
      </if>
      <if test="fundoutType != null">
        #{fundoutType,jdbcType=VARCHAR},
      </if>
      <if test="autoFundoutFlag != null">
        #{autoFundoutFlag,jdbcType=VARCHAR},
      </if>
      <if test="fundoutStatus != null">
        #{fundoutStatus,jdbcType=VARCHAR},
      </if>
      <if test="fundoutId != null">
        #{fundoutId,jdbcType=VARCHAR},
      </if>
      <if test="fundoutRequestTime != null">
        #{fundoutRequestTime,jdbcType=TIMESTAMP},
      </if>
      <if test="fundoutCompleteTime != null">
        #{fundoutCompleteTime,jdbcType=TIMESTAMP},
      </if>
      <if test="gmtCreateTime != null">
        #{gmtCreateTime,jdbcType=TIMESTAMP},
      </if>
      <if test="gmtUpdateTime != null">
        #{gmtUpdateTime,jdbcType=TIMESTAMP},
      </if>
    </trim>
  </insert>
  <update id="updateByPrimaryKeySelective" parameterType="com.ipaylinks.cmp.css.dal.model.WithdrawVoucher">
    <!--
      @MBG Generated
      This element is automatically generated by MyBatis Generator,Do not modify ! Generated on Thu May 24 17:03:46 CST 2018.
    -->
    update T_WITHDRAW_VOUCHER
    <set>
      <if test="merchantId != null">
        MERCHANT_ID = #{merchantId,jdbcType=VARCHAR},
      </if>
      <if test="fundoutTime != null">
        FUNDOUT_TIME = #{fundoutTime,jdbcType=TIMESTAMP},
      </if>
      <if test="fundoutCurrencyCode != null">
        FUNDOUT_CURRENCY_CODE = #{fundoutCurrencyCode,jdbcType=VARCHAR},
      </if>
      <if test="fundoutAmount != null">
        FUNDOUT_AMOUNT = #{fundoutAmount,jdbcType=DECIMAL},
      </if>
      <if test="beginDate != null">
        BEGIN_DATE = #{beginDate,jdbcType=VARCHAR},
      </if>
      <if test="endDate != null">
        END_DATE = #{endDate,jdbcType=VARCHAR},
      </if>
      <if test="fundoutType != null">
        FUNDOUT_TYPE = #{fundoutType,jdbcType=VARCHAR},
      </if>
      <if test="autoFundoutFlag != null">
        AUTO_FUNDOUT_FLAG = #{autoFundoutFlag,jdbcType=VARCHAR},
      </if>
      <if test="fundoutStatus != null">
        FUNDOUT_STATUS = #{fundoutStatus,jdbcType=VARCHAR},
      </if>
      <if test="fundoutId != null">
        FUNDOUT_ID = #{fundoutId,jdbcType=VARCHAR},
      </if>
      <if test="fundoutRequestTime != null">
        FUNDOUT_REQUEST_TIME = #{fundoutRequestTime,jdbcType=TIMESTAMP},
      </if>
      <if test="fundoutCompleteTime != null">
        FUNDOUT_COMPLETE_TIME = #{fundoutCompleteTime,jdbcType=TIMESTAMP},
      </if>
      <if test="gmtCreateTime != null">
        GMT_CREATE_TIME = #{gmtCreateTime,jdbcType=TIMESTAMP},
      </if>
      <if test="gmtUpdateTime != null">
        GMT_UPDATE_TIME = #{gmtUpdateTime,jdbcType=TIMESTAMP},
      </if>
    </set>
    where ID = #{id,jdbcType=VARCHAR}
  </update>
  <update id="updateByPrimaryKey" parameterType="com.ipaylinks.cmp.css.dal.model.WithdrawVoucher">
    <!--
      @MBG Generated
      This element is automatically generated by MyBatis Generator,Do not modify ! Generated on Thu May 24 17:03:46 CST 2018.
    -->
    update T_WITHDRAW_VOUCHER
    set MERCHANT_ID = #{merchantId,jdbcType=VARCHAR},
      FUNDOUT_TIME = #{fundoutTime,jdbcType=TIMESTAMP},
      FUNDOUT_CURRENCY_CODE = #{fundoutCurrencyCode,jdbcType=VARCHAR},
      FUNDOUT_AMOUNT = #{fundoutAmount,jdbcType=DECIMAL},
      BEGIN_DATE = #{beginDate,jdbcType=VARCHAR},
      END_DATE = #{endDate,jdbcType=VARCHAR},
      FUNDOUT_TYPE = #{fundoutType,jdbcType=VARCHAR},
      AUTO_FUNDOUT_FLAG = #{autoFundoutFlag,jdbcType=VARCHAR},
      FUNDOUT_STATUS = #{fundoutStatus,jdbcType=VARCHAR},
      FUNDOUT_ID = #{fundoutId,jdbcType=VARCHAR},
      FUNDOUT_REQUEST_TIME = #{fundoutRequestTime,jdbcType=TIMESTAMP},
      FUNDOUT_COMPLETE_TIME = #{fundoutCompleteTime,jdbcType=TIMESTAMP},
      GMT_CREATE_TIME = #{gmtCreateTime,jdbcType=TIMESTAMP},
      GMT_UPDATE_TIME = #{gmtUpdateTime,jdbcType=TIMESTAMP}
    where ID = #{id,jdbcType=VARCHAR}
  </update>
</mapper>